{"commands.category":"Vzdálené tunely","commands.connectCurrentWindowToTunnel.title":"Připojit k tunelu...","commands.getStarted.title":"Začínáme s tunely","commands.openOnDesktop.title":"Pokračovat v práci ve VS Code pro desktop","commands.reportIssue.title":"Nahlásit problém…","commands.settings.title":"Nastavení","configuration.title":"Vzdálené – tunely","description":"Připojení ke vzdálenému počítači prostřednictvím aplikace Tunnel","settings.alwaysUpdateCLI.description":"Pokud je k dispozici aktualizace, vždy aktualizujte rozhraní příkazového řádku VS Code CLI.","viewsWelcome.explorer.web":"To connect to a machine that has Remote Tunnel Access enabled or learn about how to do that, click here:\r\n[Connect to Tunnel...](command:remote-tunnels.connectCurrentWindowToTunnel)"}
